pytest_structlog/__init__.py
pytest_structlog/py.typed
pytest_structlog-1.2.dist-info/licenses/LICENSE
pytest_structlog-1.2.dist-info/METADATA
pytest_structlog-1.2.dist-info/WHEEL
pytest_structlog-1.2.dist-info/entry_points.txt
pytest_structlog-1.2.dist-info/top_level.txt
pytest_structlog-1.2.dist-info/RECORD
