Metadata-Version: 2.4
Name: pytest-structlog
Version: 1.2
Summary: Structured logging assertions
Author-email: Wim Glenn <hey@wimglenn.com>
License-Expression: MIT
Project-URL: Homepage, https://github.com/wimglenn/pytest-structlog
Classifier: Framework :: Pytest
Classifier: Programming Language :: Python
Classifier: Programming Language :: Python :: 3
Requires-Python: >=3.8
License-File: LICENSE
Requires-Dist: pytest
Requires-Dist: structlog>=22.2.0
Dynamic: license-file
